termipy/__init__.py
termipy/base_command.py
termipy/docs.py
termipy/environment_commands.py
termipy/file_commands.py
termipy/main.py
termipy/resource_commands.py
termipy/shell.py
termipy/system_commands.py
termipy/utility_commands.py
termipy/utils.py
termipy-0.2.7.dist-info/LICENSE
termipy-0.2.7.dist-info/METADATA
termipy-0.2.7.dist-info/WHEEL
termipy-0.2.7.dist-info/entry_points.txt
termipy-0.2.7.dist-info/top_level.txt
termipy-0.2.7.dist-info/RECORD
