Metadata-Version: 2.1
Name: termipy
Version: 0.2.7
Summary: A versatile command-line shell with system monitoring capabilities
Home-page: https://github.com/pr2tik1/termipy
Author: Pratik Kumar
Author-email: pr2tik1@gmail.com
Classifier: Programming Language :: Python :: 3
Classifier: License :: OSI Approved :: MIT License
Classifier: Operating System :: OS Independent
Requires-Python: >=3.6
License-File: LICENSE
Requires-Dist: psutil
Requires-Dist: colorama
Provides-Extra: test
Requires-Dist: pytest >=6.2.5 ; extra == 'test'
Requires-Dist: pytest-cov >=2.12.1 ; extra == 'test'
